LICENSE
MANIFEST.in
README.md
setup.py
tap_mailshake/__init__.py
tap_mailshake/client.py
tap_mailshake/discover.py
tap_mailshake/schema.py
tap_mailshake/streams.py
tap_mailshake/sync.py
tap_mailshake/transform.py
tap_mailshake.egg-info/PKG-INFO
tap_mailshake.egg-info/SOURCES.txt
tap_mailshake.egg-info/dependency_links.txt
tap_mailshake.egg-info/entry_points.txt
tap_mailshake.egg-info/requires.txt
tap_mailshake.egg-info/top_level.txt
tap_mailshake/schemas/campaigns.json
tap_mailshake/schemas/clicks.json
tap_mailshake/schemas/leads.json
tap_mailshake/schemas/opens.json
tap_mailshake/schemas/recipients.json
tap_mailshake/schemas/replies.json
tap_mailshake/schemas/senders.json
tap_mailshake/schemas/sent_messages.json
tap_mailshake/schemas/team_members.json
tap_mailshake/tests/denest_recursive_nodes_data.py
tap_mailshake/tests/test_denest.py