Metadata-Version: 1.1
Name: tap-mailshake
Version: 0.0.4
Summary: Singer.io tap for extracting data from the Mailshake API
Home-page: UNKNOWN
Author: nick.civili@bytecode.io
Author-email: UNKNOWN
License: UNKNOWN
Platform: UNKNOWN
Classifier: Programming Language :: Python :: 3 :: Only
